AORT.py
aort-1.7.data/scripts/aort
aort-1.7.dist-info/LICENSE
aort-1.7.dist-info/METADATA
aort-1.7.dist-info/WHEEL
aort-1.7.dist-info/top_level.txt
aort-1.7.dist-info/RECORD
